{
	"version":1.0,
	"people":[
		{
			"pose_keypoints":[
				0,0,0,0,0,0,0,0,0,0,0,0,0,0,0,0,0,0,0,0,0,0,0,0,28.8748,70.6072,0.190047,29.2117,96.0107,0.538981,41.0421,113.04,0.480366,0,0,0,0,0,0,0,0,0,0,0,0,0,0,0,0,0,0,0,0,0
			],
			"face_keypoints":[
				
			],
			"hand_left_keypoints":[
				
			],
			"hand_right_keypoints":[
				
			]
		},
		{
			"pose_keypoints":[
				0,0,0,0,0,0,0,0,0,0,0,0,0,0,0,0,0,0,0,0,0,0,0,0,0,0,0,0,0,0,0,0,0,16.6934,69.2159,0.13957,7.65945,95.2967,0.536063,6.96485,117.914,0.518906,0,0,0,0,0,0,0,0,0,0,0,0
			],
			"face_keypoints":[
				
			],
			"hand_left_keypoints":[
				
			],
			"hand_right_keypoints":[
				
			]
		}
	]
}
